<?xml version="1.0" encoding="UTF-8" standalone="yes"?>
<xdr:wsDr xmlns:xdr="http://schemas.openxmlformats.org/drawingml/2006/spreadsheetDrawing" xmlns:a="http://schemas.openxmlformats.org/drawingml/2006/main"><xdr:twoCellAnchor><xdr:from><xdr:col>16</xdr:col><xdr:colOff>0</xdr:colOff><xdr:row>2</xdr:row><xdr:rowOff>139700</xdr:rowOff></xdr:from><xdr:to><xdr:col>16</xdr:col><xdr:colOff>0</xdr:colOff><xdr:row>3</xdr:row><xdr:rowOff>138804</xdr:rowOff></xdr:to><xdr:sp macro="" textlink=""><xdr:nvSpPr><xdr:cNvPr id="7413" name="Rectangle 187"><a:extLst><a:ext uri="{FF2B5EF4-FFF2-40B4-BE49-F238E27FC236}"><a16:creationId xmlns:a16="http://schemas.microsoft.com/office/drawing/2014/main" id="{D05D4821-5ACA-EFD0-4229-78FC8E1E114A}"/></a:ext></a:extLst></xdr:cNvPr><xdr:cNvSpPr><a:spLocks noChangeArrowheads="1"/></xdr:cNvSpPr></xdr:nvSpPr><xdr:spPr bwMode="auto"><a:xfrm><a:off x="6248400" y="444500"/><a:ext cx="0" cy="215900"/></a:xfrm><a:prstGeom prst="rect"><a:avLst/></a:prstGeom><a:solidFill><a:srgbClr val="FFFFFF" xmlns:mc="http://schemas.openxmlformats.org/markup-compatibility/2006" mc:Ignorable="a14" xmlns:a14="http://schemas.microsoft.com/office/drawing/2010/main" a14:legacySpreadsheetColorIndex="9"/></a:solidFill><a:ln w="1"><a:solidFill><a:srgbClr val="FFFFFF" xmlns:mc="http://schemas.openxmlformats.org/markup-compatibility/2006" mc:Ignorable="a14" xmlns:a14="http://schemas.microsoft.com/office/drawing/2010/main" a14:legacySpreadsheetColorIndex="9"/></a:solidFill><a:miter lim="800000"/><a:headEnd/><a:tailEnd/></a:ln></xdr:spPr><xdr:txBody><a:bodyPr rtlCol="0"/><a:lstStyle/><a:p><a:pPr algn="ctr"/><a:endParaRPr lang="en-US"/></a:p></xdr:txBody></xdr:sp><xdr:clientData/></xdr:twoCellAnchor><mc:AlternateContent xmlns:mc="http://schemas.openxmlformats.org/markup-compatibility/2006"><mc:Choice xmlns:a14="http://schemas.microsoft.com/office/drawing/2010/main" Requires="a14"><xdr:twoCellAnchor><xdr:from><xdr:col>0</xdr:col><xdr:colOff>50800</xdr:colOff><xdr:row>0</xdr:row><xdr:rowOff>50800</xdr:rowOff></xdr:from><xdr:to><xdr:col>1</xdr:col><xdr:colOff>444500</xdr:colOff><xdr:row>0</xdr:row><xdr:rowOff>228600</xdr:rowOff></xdr:to><xdr:sp macro="" textlink=""><xdr:nvSpPr><xdr:cNvPr id="7373" name="Button 205" hidden="1"><a:extLst><a:ext uri="{63B3BB69-23CF-44E3-9099-C40C66FF867C}"><a14:compatExt spid="_x0000_s7373"/></a:ext><a:ext uri="{FF2B5EF4-FFF2-40B4-BE49-F238E27FC236}"><a16:creationId xmlns:a16="http://schemas.microsoft.com/office/drawing/2014/main" id="{180B2EF0-5400-92F0-D326-C5337462DC2D}"/></a:ext></a:extLst></xdr:cNvPr><xdr:cNvSpPr/></xdr:nvSpPr><xdr:spPr bwMode="auto"><a:xfrm><a:off x="0" y="0"/><a:ext cx="0" cy="0"/></a:xfrm><a:prstGeom prst="rect"><a:avLst/></a:prstGeom><a:noFill/><a:ln><a:noFill/></a:ln><a:effectLst/><a:extLst><a:ext uri="{91240B29-F687-4F45-9708-019B960494DF}"><a14:hiddenLine w="9525"><a:noFill/><a:miter lim="800000"/><a:headEnd/><a:tailEnd/></a14:hiddenLine></a:ext><a:ext uri="{AF507438-7753-43E0-B8FC-AC1667EBCBE1}"><a14:hiddenEffects><a:effectLst><a:outerShdw dist="35921" dir="2700000" algn="ctr" rotWithShape="0"><a:srgbClr val="808080"/></a:outerShdw></a:effectLst></a14:hiddenEffects></a:ext></a:extLst></xdr:spPr><xdr:txBody><a:bodyPr vertOverflow="clip" wrap="square" lIns="18288" tIns="18288" rIns="18288" bIns="18288" anchor="ctr" upright="1"/><a:lstStyle/><a:p><a:pPr algn="ctr" rtl="0"><a:defRPr sz="1000"/></a:pPr><a:r><a:rPr lang="en-US" sz="700" b="0" i="0" u="none" strike="noStrike" baseline="0"><a:solidFill><a:srgbClr val="808080"/></a:solidFill><a:latin typeface="Arial" pitchFamily="2" charset="-52"/><a:cs typeface="Arial" pitchFamily="2" charset="-52"/></a:rPr><a:t>Send Actuals</a:t></a:r></a:p></xdr:txBody></xdr:sp><xdr:clientData fPrintsWithSheet="0"/></xdr:twoCellAnchor></mc:Choice><mc:Fallback/></mc:AlternateContent><mc:AlternateContent xmlns:mc="http://schemas.openxmlformats.org/markup-compatibility/2006"><mc:Choice xmlns:a14="http://schemas.microsoft.com/office/drawing/2010/main" Requires="a14"><xdr:twoCellAnchor><xdr:from><xdr:col>1</xdr:col><xdr:colOff>508000</xdr:colOff><xdr:row>0</xdr:row><xdr:rowOff>50800</xdr:rowOff></xdr:from><xdr:to><xdr:col>1</xdr:col><xdr:colOff>863600</xdr:colOff><xdr:row>0</xdr:row><xdr:rowOff>228600</xdr:rowOff></xdr:to><xdr:sp macro="" textlink=""><xdr:nvSpPr><xdr:cNvPr id="7374" name="Button 206" hidden="1"><a:extLst><a:ext uri="{63B3BB69-23CF-44E3-9099-C40C66FF867C}"><a14:compatExt spid="_x0000_s7374"/></a:ext><a:ext uri="{FF2B5EF4-FFF2-40B4-BE49-F238E27FC236}"><a16:creationId xmlns:a16="http://schemas.microsoft.com/office/drawing/2014/main" id="{2F38CCAF-EF48-6EEB-8277-C5FB01C3DC8C}"/></a:ext></a:extLst></xdr:cNvPr><xdr:cNvSpPr/></xdr:nvSpPr><xdr:spPr bwMode="auto"><a:xfrm><a:off x="0" y="0"/><a:ext cx="0" cy="0"/></a:xfrm><a:prstGeom prst="rect"><a:avLst/></a:prstGeom><a:noFill/><a:ln><a:noFill/></a:ln><a:effectLst/><a:extLst><a:ext uri="{91240B29-F687-4F45-9708-019B960494DF}"><a14:hiddenLine w="9525"><a:noFill/><a:miter lim="800000"/><a:headEnd/><a:tailEnd/></a14:hiddenLine></a:ext><a:ext uri="{AF507438-7753-43E0-B8FC-AC1667EBCBE1}"><a14:hiddenEffects><a:effectLst><a:outerShdw dist="35921" dir="2700000" algn="ctr" rotWithShape="0"><a:srgbClr val="808080"/></a:outerShdw></a:effectLst></a14:hiddenEffects></a:ext></a:extLst></xdr:spPr><xdr:txBody><a:bodyPr vertOverflow="clip" wrap="square" lIns="18288" tIns="18288" rIns="18288" bIns="18288" anchor="ctr" upright="1"/><a:lstStyle/><a:p><a:pPr algn="ctr" rtl="0"><a:defRPr sz="1000"/></a:pPr><a:r><a:rPr lang="en-US" sz="700" b="0" i="0" u="none" strike="noStrike" baseline="0"><a:solidFill><a:srgbClr val="808080"/></a:solidFill><a:latin typeface="Arial" pitchFamily="2" charset="-52"/><a:cs typeface="Arial" pitchFamily="2" charset="-52"/></a:rPr><a:t>Print</a:t></a:r></a:p></xdr:txBody></xdr:sp><xdr:clientData fPrintsWithSheet="0"/></xdr:twoCellAnchor></mc:Choice><mc:Fallback/></mc:AlternateContent><mc:AlternateContent xmlns:mc="http://schemas.openxmlformats.org/markup-compatibility/2006"><mc:Choice xmlns:a14="http://schemas.microsoft.com/office/drawing/2010/main" Requires="a14"><xdr:twoCellAnchor><xdr:from><xdr:col>29</xdr:col><xdr:colOff>88900</xdr:colOff><xdr:row>2</xdr:row><xdr:rowOff>9448800</xdr:rowOff></xdr:from><xdr:to><xdr:col>29</xdr:col><xdr:colOff>673100</xdr:colOff><xdr:row>3</xdr:row><xdr:rowOff>21234400</xdr:rowOff></xdr:to><xdr:sp macro="" textlink=""><xdr:nvSpPr><xdr:cNvPr id="7376" name="Button 208" hidden="1"><a:extLst><a:ext uri="{63B3BB69-23CF-44E3-9099-C40C66FF867C}"><a14:compatExt spid="_x0000_s7376"/></a:ext><a:ext uri="{FF2B5EF4-FFF2-40B4-BE49-F238E27FC236}"><a16:creationId xmlns:a16="http://schemas.microsoft.com/office/drawing/2014/main" id="{9C0FAF91-AE5C-59D1-6D44-5B28AC8E14C9}"/></a:ext></a:extLst></xdr:cNvPr><xdr:cNvSpPr/></xdr:nvSpPr><xdr:spPr bwMode="auto"><a:xfrm><a:off x="0" y="0"/><a:ext cx="0" cy="0"/></a:xfrm><a:prstGeom prst="rect"><a:avLst/></a:prstGeom><a:noFill/><a:ln><a:noFill/></a:ln><a:effectLst/><a:extLst><a:ext uri="{91240B29-F687-4F45-9708-019B960494DF}"><a14:hiddenLine w="9525"><a:noFill/><a:miter lim="800000"/><a:headEnd/><a:tailEnd/></a14:hiddenLine></a:ext><a:ext uri="{AF507438-7753-43E0-B8FC-AC1667EBCBE1}"><a14:hiddenEffects><a:effectLst><a:outerShdw dist="35921" dir="2700000" algn="ctr" rotWithShape="0"><a:srgbClr val="808080"/></a:outerShdw></a:effectLst></a14:hiddenEffects></a:ext></a:extLst></xdr:spPr><xdr:txBody><a:bodyPr vertOverflow="clip" wrap="square" lIns="18288" tIns="18288" rIns="18288" bIns="18288" anchor="ctr" upright="1"/><a:lstStyle/><a:p><a:pPr algn="ctr" rtl="0"><a:defRPr sz="1000"/></a:pPr><a:r><a:rPr lang="en-US" sz="700" b="0" i="0" u="none" strike="noStrike" baseline="0"><a:solidFill><a:srgbClr val="808080"/></a:solidFill><a:latin typeface="Arial" pitchFamily="2" charset="-52"/><a:cs typeface="Arial" pitchFamily="2" charset="-52"/></a:rPr><a:t>Act Detail</a:t></a:r></a:p></xdr:txBody></xdr:sp><xdr:clientData fPrintsWithSheet="0"/></xdr:twoCellAnchor></mc:Choice><mc:Fallback/></mc:AlternateContent><mc:AlternateContent xmlns:mc="http://schemas.openxmlformats.org/markup-compatibility/2006"><mc:Choice xmlns:a14="http://schemas.microsoft.com/office/drawing/2010/main" Requires="a14"><xdr:twoCellAnchor><xdr:from><xdr:col>6</xdr:col><xdr:colOff>63500</xdr:colOff><xdr:row>2</xdr:row><xdr:rowOff>7112000</xdr:rowOff></xdr:from><xdr:to><xdr:col>7</xdr:col><xdr:colOff>203200</xdr:colOff><xdr:row>3</xdr:row><xdr:rowOff>18897600</xdr:rowOff></xdr:to><xdr:sp macro="" textlink=""><xdr:nvSpPr><xdr:cNvPr id="7378" name="Button 210" hidden="1"><a:extLst><a:ext uri="{63B3BB69-23CF-44E3-9099-C40C66FF867C}"><a14:compatExt spid="_x0000_s7378"/></a:ext><a:ext uri="{FF2B5EF4-FFF2-40B4-BE49-F238E27FC236}"><a16:creationId xmlns:a16="http://schemas.microsoft.com/office/drawing/2014/main" id="{4911A9DD-E628-F932-740A-8B28DABBC405}"/></a:ext></a:extLst></xdr:cNvPr><xdr:cNvSpPr/></xdr:nvSpPr><xdr:spPr bwMode="auto"><a:xfrm><a:off x="0" y="0"/><a:ext cx="0" cy="0"/></a:xfrm><a:prstGeom prst="rect"><a:avLst/></a:prstGeom><a:noFill/><a:ln><a:noFill/></a:ln><a:effectLst/><a:extLst><a:ext uri="{91240B29-F687-4F45-9708-019B960494DF}"><a14:hiddenLine w="9525"><a:noFill/><a:miter lim="800000"/><a:headEnd/><a:tailEnd/></a14:hiddenLine></a:ext><a:ext uri="{AF507438-7753-43E0-B8FC-AC1667EBCBE1}"><a14:hiddenEffects><a:effectLst><a:outerShdw dist="35921" dir="2700000" algn="ctr" rotWithShape="0"><a:srgbClr val="808080"/></a:outerShdw></a:effectLst></a14:hiddenEffects></a:ext></a:extLst></xdr:spPr><xdr:txBody><a:bodyPr vertOverflow="clip" wrap="square" lIns="18288" tIns="18288" rIns="18288" bIns="18288" anchor="ctr" upright="1"/><a:lstStyle/><a:p><a:pPr algn="ctr" rtl="0"><a:defRPr sz="1000"/></a:pPr><a:r><a:rPr lang="en-US" sz="700" b="0" i="0" u="none" strike="noStrike" baseline="0"><a:solidFill><a:srgbClr val="808080"/></a:solidFill><a:latin typeface="Arial" pitchFamily="2" charset="-52"/><a:cs typeface="Arial" pitchFamily="2" charset="-52"/></a:rPr><a:t>Est Detail</a:t></a:r></a:p></xdr:txBody></xdr:sp><xdr:clientData fPrintsWithSheet="0"/></xdr:twoCellAnchor></mc:Choice><mc:Fallback/></mc:AlternateContent><mc:AlternateContent xmlns:mc="http://schemas.openxmlformats.org/markup-compatibility/2006"><mc:Choice xmlns:a14="http://schemas.microsoft.com/office/drawing/2010/main" Requires="a14"><xdr:twoCellAnchor><xdr:from><xdr:col>14</xdr:col><xdr:colOff>0</xdr:colOff><xdr:row>2</xdr:row><xdr:rowOff>7112000</xdr:rowOff></xdr:from><xdr:to><xdr:col>14</xdr:col><xdr:colOff>0</xdr:colOff><xdr:row>3</xdr:row><xdr:rowOff>18897600</xdr:rowOff></xdr:to><xdr:sp macro="" textlink=""><xdr:nvSpPr><xdr:cNvPr id="7379" name="Button 211" hidden="1"><a:extLst><a:ext uri="{63B3BB69-23CF-44E3-9099-C40C66FF867C}"><a14:compatExt spid="_x0000_s7379"/></a:ext><a:ext uri="{FF2B5EF4-FFF2-40B4-BE49-F238E27FC236}"><a16:creationId xmlns:a16="http://schemas.microsoft.com/office/drawing/2014/main" id="{8215BB18-6758-0A63-946C-6043BF74FFDB}"/></a:ext></a:extLst></xdr:cNvPr><xdr:cNvSpPr/></xdr:nvSpPr><xdr:spPr bwMode="auto"><a:xfrm><a:off x="0" y="0"/><a:ext cx="0" cy="0"/></a:xfrm><a:prstGeom prst="rect"><a:avLst/></a:prstGeom><a:noFill/><a:ln><a:noFill/></a:ln><a:effectLst/><a:extLst><a:ext uri="{91240B29-F687-4F45-9708-019B960494DF}"><a14:hiddenLine w="9525"><a:noFill/><a:miter lim="800000"/><a:headEnd/><a:tailEnd/></a14:hiddenLine></a:ext><a:ext uri="{AF507438-7753-43E0-B8FC-AC1667EBCBE1}"><a14:hiddenEffects><a:effectLst><a:outerShdw dist="35921" dir="2700000" algn="ctr" rotWithShape="0"><a:srgbClr val="808080"/></a:outerShdw></a:effectLst></a14:hiddenEffects></a:ext></a:extLst></xdr:spPr><xdr:txBody><a:bodyPr vertOverflow="clip" wrap="square" lIns="18288" tIns="18288" rIns="18288" bIns="18288" anchor="ctr" upright="1"/><a:lstStyle/><a:p><a:pPr algn="ctr" rtl="0"><a:defRPr sz="1000"/></a:pPr><a:r><a:rPr lang="en-US" sz="700" b="0" i="0" u="none" strike="noStrike" baseline="0"><a:solidFill><a:srgbClr val="808080"/></a:solidFill><a:latin typeface="Arial" pitchFamily="2" charset="-52"/><a:cs typeface="Arial" pitchFamily="2" charset="-52"/></a:rPr><a:t>OT Calc</a:t></a:r></a:p></xdr:txBody></xdr:sp><xdr:clientData fPrintsWithSheet="0"/></xdr:twoCellAnchor></mc:Choice><mc:Fallback/></mc:AlternateContent><mc:AlternateContent xmlns:mc="http://schemas.openxmlformats.org/markup-compatibility/2006"><mc:Choice xmlns:a14="http://schemas.microsoft.com/office/drawing/2010/main" Requires="a14"><xdr:twoCellAnchor><xdr:from><xdr:col>29</xdr:col><xdr:colOff>88900</xdr:colOff><xdr:row>0</xdr:row><xdr:rowOff>50800</xdr:rowOff></xdr:from><xdr:to><xdr:col>29</xdr:col><xdr:colOff>673100</xdr:colOff><xdr:row>0</xdr:row><xdr:rowOff>228600</xdr:rowOff></xdr:to><xdr:sp macro="" textlink=""><xdr:nvSpPr><xdr:cNvPr id="7380" name="Button 212" hidden="1"><a:extLst><a:ext uri="{63B3BB69-23CF-44E3-9099-C40C66FF867C}"><a14:compatExt spid="_x0000_s7380"/></a:ext><a:ext uri="{FF2B5EF4-FFF2-40B4-BE49-F238E27FC236}"><a16:creationId xmlns:a16="http://schemas.microsoft.com/office/drawing/2014/main" id="{DDAD395E-51B9-CA7B-9CA3-B20E2A2CD8C4}"/></a:ext></a:extLst></xdr:cNvPr><xdr:cNvSpPr/></xdr:nvSpPr><xdr:spPr bwMode="auto"><a:xfrm><a:off x="0" y="0"/><a:ext cx="0" cy="0"/></a:xfrm><a:prstGeom prst="rect"><a:avLst/></a:prstGeom><a:noFill/><a:ln><a:noFill/></a:ln><a:effectLst/><a:extLst><a:ext uri="{91240B29-F687-4F45-9708-019B960494DF}"><a14:hiddenLine w="9525"><a:noFill/><a:miter lim="800000"/><a:headEnd/><a:tailEnd/></a14:hiddenLine></a:ext><a:ext uri="{AF507438-7753-43E0-B8FC-AC1667EBCBE1}"><a14:hiddenEffects><a:effectLst><a:outerShdw dist="35921" dir="2700000" algn="ctr" rotWithShape="0"><a:srgbClr val="808080"/></a:outerShdw></a:effectLst></a14:hiddenEffects></a:ext></a:extLst></xdr:spPr><xdr:txBody><a:bodyPr vertOverflow="clip" wrap="square" lIns="18288" tIns="18288" rIns="18288" bIns="18288" anchor="ctr" upright="1"/><a:lstStyle/><a:p><a:pPr algn="ctr" rtl="0"><a:defRPr sz="1000"/></a:pPr><a:r><a:rPr lang="en-US" sz="700" b="0" i="0" u="none" strike="noStrike" baseline="0"><a:solidFill><a:srgbClr val="808080"/></a:solidFill><a:latin typeface="Arial" pitchFamily="2" charset="-52"/><a:cs typeface="Arial" pitchFamily="2" charset="-52"/></a:rPr><a:t>Working</a:t></a:r></a:p></xdr:txBody></xdr:sp><xdr:clientData fPrintsWithSheet="0"/></xdr:twoCellAnchor></mc:Choice><mc:Fallback/></mc:AlternateContent><mc:AlternateContent xmlns:mc="http://schemas.openxmlformats.org/markup-compatibility/2006"><mc:Choice xmlns:a14="http://schemas.microsoft.com/office/drawing/2010/main" Requires="a14"><xdr:twoCellAnchor><xdr:from><xdr:col>14</xdr:col><xdr:colOff>0</xdr:colOff><xdr:row>0</xdr:row><xdr:rowOff>50800</xdr:rowOff></xdr:from><xdr:to><xdr:col>14</xdr:col><xdr:colOff>0</xdr:colOff><xdr:row>0</xdr:row><xdr:rowOff>228600</xdr:rowOff></xdr:to><xdr:sp macro="" textlink=""><xdr:nvSpPr><xdr:cNvPr id="7381" name="Button 213" hidden="1"><a:extLst><a:ext uri="{63B3BB69-23CF-44E3-9099-C40C66FF867C}"><a14:compatExt spid="_x0000_s7381"/></a:ext><a:ext uri="{FF2B5EF4-FFF2-40B4-BE49-F238E27FC236}"><a16:creationId xmlns:a16="http://schemas.microsoft.com/office/drawing/2014/main" id="{E46D7A9C-BF4D-B85A-B126-A0FAB8452CE0}"/></a:ext></a:extLst></xdr:cNvPr><xdr:cNvSpPr/></xdr:nvSpPr><xdr:spPr bwMode="auto"><a:xfrm><a:off x="0" y="0"/><a:ext cx="0" cy="0"/></a:xfrm><a:prstGeom prst="rect"><a:avLst/></a:prstGeom><a:noFill/><a:ln><a:noFill/></a:ln><a:effectLst/><a:extLst><a:ext uri="{91240B29-F687-4F45-9708-019B960494DF}"><a14:hiddenLine w="9525"><a:noFill/><a:miter lim="800000"/><a:headEnd/><a:tailEnd/></a14:hiddenLine></a:ext><a:ext uri="{AF507438-7753-43E0-B8FC-AC1667EBCBE1}"><a14:hiddenEffects><a:effectLst><a:outerShdw dist="35921" dir="2700000" algn="ctr" rotWithShape="0"><a:srgbClr val="808080"/></a:outerShdw></a:effectLst></a14:hiddenEffects></a:ext></a:extLst></xdr:spPr><xdr:txBody><a:bodyPr vertOverflow="clip" wrap="square" lIns="18288" tIns="18288" rIns="18288" bIns="18288" anchor="ctr" upright="1"/><a:lstStyle/><a:p><a:pPr algn="ctr" rtl="0"><a:defRPr sz="1000"/></a:pPr><a:r><a:rPr lang="en-US" sz="700" b="0" i="0" u="none" strike="noStrike" baseline="0"><a:solidFill><a:srgbClr val="808080"/></a:solidFill><a:latin typeface="Arial" pitchFamily="2" charset="-52"/><a:cs typeface="Arial" pitchFamily="2" charset="-52"/></a:rPr><a:t>Actual</a:t></a:r></a:p></xdr:txBody></xdr:sp><xdr:clientData fPrintsWithSheet="0"/></xdr:twoCellAnchor></mc:Choice><mc:Fallback/></mc:AlternateContent></xdr:wsDr>